{
  "id": "1_57",
  "title": "Chapitre 57",
  "lieu": "Essaouira, Maroc",
  "heure": "20:45",
  "texte": "Plage de Tagharte face à l’Atlantique. Soleil revenu à une morsure plus douce. Les enfants de Chahid bodysurfent les rouleaux pendant que lui-même ne décolle pas d’InLine. La révélation de Sara Cash lui procure un plaisir extrême, elle sonne comme une consécration.\n\nDix ans plus tôt, il a découvert des cristaux de sucre dans l’espace interstellaire : une des briques indispensables au vivant. Il a même publié un livre destiné au grand public, *L’analogie du loto*, où il explique que les joueurs ont peu de chance de gagner, mais comme ils misent par millions, quelques-uns emportent le gros lot. Idem dans les étoiles : 200 milliards rien que dans la Voie lactée, ça implique pas mal de jackpots.\n\nIl restait la possibilité que l’humanité soit la première civilisation. Il faut croire que non. Nous n’avons pas le privilège de l’ancienneté.\n\n— Papa, viens te baigner.\n\n— J’arrive.\n\nIl fait toujours cette promesse. Souvent, quand il se décide, ses enfants sont fatigués de l’attendre. Il en éprouve une pénible frustration. Ils le punissent à leur façon en demandant de rentrer à la maison. Le bain, c’est maintenant. Dans une heure, la vidéo de Sara Cash n’aura pas disparu du réseau. Alors Chahid devrait choisir le bain, choisir ce qui ne se répétera pas, ce moment de jeu et de joie pure.\n\nIl hésite, voudrait faire deux choses en même temps, mais est incapable de l’une et de l’autre. Il regarde l’infographie du système Gliese 581 avec son cortège de planètes détectées par le télescope spatial New Kepler, puis se tourne vers ses enfants. Pour eux, une vague est plus extraordinaire qu’un contact avec des extraterrestres.\n\nChahid les approuve, en toute probabilité le contact est un canular ou une erreur d’analyse. Pourtant les données semblent solides. Se pose la question du message, de son contenu, de ses conséquences.\n\n— Papa.\n\nChahid abandonne sa tablette sur la serviette, il marche vers le rivage. Ses orteils creusent le sable chaud. Une force monte en lui du plus profond de la terre. Il se sent vivre."
}