{
  "id": "2_21",
  "title": "Chapitre 21",
  "lieu": "Santa Fe, États-Unis",
  "heure": "13:45",
  "texte": "Quand on descend de l’institut par Gonzales Road, on tombe directement sur la cantina El Farol, où l’annonce de Sara Cash ne trouble guère les conversations de comptoir.\n\n— Comme une civilisation regroupe des individus, elle est plus complexe que chacun d’eux. Donc, soit nous autres humains sommes loin du maximum de complexité, soit la théorie de la jeune Mackenzie est fausse.\n\n— Non, la complexité se mesure à l’échelle du réseau. Un cerveau rassemble 100 milliards de neurones, dont 100 millions se situent d’ailleurs dans l’intestin. Il faut chercher dans ces ordres de grandeur le plafond de verre : une civilisation de 100 milliards d’agents autonomes, biologiques ou non.\n\n— Tu sous-entends que la complexité ne se transmet pas d’une échelle fractale à l’autre. Ce qui est dans le cerveau y reste.\n\n— Mes neurones ne sont pas connectés aux tiens. C’est toi et moi, des structures émergentes, qui contribuons à la société, pas nos cellules.\n\n— Je pense à la théorie de Joseph Tainter : une civilisation s’effondre quand elle manque d’énergie afin de poursuivre sa complexification. En fait, le plafond de verre serait inaccessible à l’échelle d’une planète.\n\n— Sauf que la complexification n’est pas nécessairement liée à l’énergie. S’il est vrai que plus on crée de routes et de voitures, plus on consomme d’énergie, rien n’empêche d’inventer d’autres systèmes de transport, basés sur de nouvelles technologies, qui pour chaque déplacement consomment moins. C’est le cas du cerveau, aussi d’un réseau numérique. Dans ce cas, plus de puissance n’implique pas plus de dépenses.\n\n— Pour qu’une civilisation continue de tendre vers plus de complexité, elle doit donc régulièrement changer de technologie.\n\n— Exactement. Si elle ne le fait pas, elle se heurte à un plafond de verre énergétique sans relation avec celui de la complexité.\n\nLes lumières du bar s’éteignent. Le serveur qui était accoudé en face des deux scientifiques paraît exaspéré.\n\n— Bon, les filles, mangez vos tortillas sinon je crois qu’elles vont refroidir. Le temps de l’effondrement est venu. On nous a coupé le robinet. Plus d’énergie pour délirer."
}