{
  "id": "2_39",
  "title": "Chapitre 39",
  "lieu": "Monkey Bay, Malawi",
  "heure": "21:45",
  "texte": "Tiwonge est une longue tige, cheveux tressés, colorés de quelques perles et noués en chignon derrière la nuque. Elle porte toujours un short orange, un t-shirt jaune. On la surnomme Soleil. Par opposition, Melina est Nuit. Déjà plus sombre de peau que son amie, elle s’accoutre maladroitement de robes tombantes, qui ne dégagent que ses fines épaules où coule une mer de boucles ébène. On leur conseille souvent d’échanger leur tenue. Melina en serait grandie et Tiwonge reviendrait à une stature moins impressionnante.\n\n— Ouf ! On a réussi à fuir ce bar pourri. Comment peuvent-ils passer leurs soirées dans ce bouge ?\n\nElles s’esclaffent, rejoignent les rochers en surplomb du lac Malawi. Elles n’ont pas besoin de voir où elles posent les pieds. Leurs orteils connaissent le galbe de la pierre depuis toujours. Melina s’assoit.\n\n— Alors tu as commencé à lire *Blackout*, l’histoire d’Aba, la chasseuse d’analystes ?\n\nTiwonge reste droite, une vigie, le regard perdu vers le firmament dépourvu d’étoiles.\n\n— J’avance tout doucement dans le roman de Neal Lover. Je reprends sans cesse. Ça me parle, là.\n\nElle tape du poing sur son cœur. Melina l’imite.\n\n— Moi aussi, je sens plus que je ne sais. Tu te souviens de cette fois où nous jouions sur la plage. Soudain, nous avons regagné la ville en courant. Quelqu’un avait mis le feu à l’école. Nous le savions.\n\n— Les analystes ne sont qu’un fantasme de Neal Lover, la coupe Tiwonge.\n\nMelina secoue la tête.\n\n— Cet auteur n’a pas choisi un pseudoridicule pour rien. Il veut nous persuader que son histoire n’est qu’une fable. Mais tu devines comme moi qu’il y a quelque chose d’autre. C’est ancré en nous.\n\n— Tu crois qu’il nous raconte sa vie ?\n\n— Ce n’est pas un romancier. Il ne sera l’auteur que d’un livre. Ça aussi je le sens. Pourquoi tu ne t’assois pas ?\n\nTiwonge tend une main à son amie.\n\n— Relève-toi. Tu n’entends rien ?\n\nD’infimes vagues recouvrent les rochers. Un poisson volant replonge dans l’eau. Des insectes crépitent. Melina se redresse. Elle garde la main de Tiwonge dans la sienne.\n\n— Je n’entends rien. Je perçois un vide immense. La nuit s’ouvre au-dessous de nous plutôt qu’au-dessus, mais je n’ai pas peur. Je suis apaisée.\n\n— Apaisée, c’est le mot exact."
}