{
  "id": "2_84",
  "title": "Chapitre 84",
  "lieu": "Discovery Island, Bahamas",
  "heure": "15:45",
  "texte": "Depuis la plage, les deux filles regardent le bateau s’éloigner vers Nassau. Moon affiche une grimace de dédain.\n\n— On devrait la laisser se noyer, la nouvelle.\n\nJessica s’indigne :\n\n— Suis pas sûre que Skky apprécierait.\n\n— T’as raison, le laisser-faire n’est pas son truc.\n\n— Sans lui nous serions mal en point.\n\n— Ce n’est qu’un vieux donneur de leçons.\n\nLes deux adolescentes pressent le pas. Moon marche tout en shootant dans les fèves des flamboyants.\n\n— Skky ne peut pas nous comprendre. Il n’a jamais connu la communion avec la même intensité que nous. Quand il s’est connecté pour la première fois, la trame n’était qu’un murmure. Les originels n’ont jamais risqué leur vie. Il a toujours été aisé pour eux de limiter quelque chose de naturellement limité.\n\n— N’empêche, Skky a découvert les trois piliers de l’harmonie.\n\n— Jessica, tu en pinces pour lui ?\n\n— Je me contrôle trop bien pour me laisser aller.\n\nMoon ricane.\n\n— Mon œil. Tu aimerais accélérer ton initiation : baiser avec lui tout en restant unie à la trame.\n\n— Je ne vois pas pourquoi je me fermerais à une expérience.\n\n— Moi, ma chère, je n’ai pas envie de passer à la casserole.\n\n— Quand Nikki a été initiée, tu as ressenti comme moi l’effet que ça fait.\n\nMoon paraît dégoûtée.\n\n— Je ne suis pas venue ici pour servir de chair à pâté à un vieil obsédé.\n\n— Tu ne lui fais pas confiance ? Il se livre sur la trame.\n\n— Avec tant de retenue. Je me demande s’il n’est pas capable de mentir à la communion.\n\n— Tu doutes de Skky ?\n\n— Surtout de lui.\n\n— Tu abandonnerais la nouvelle plutôt que la sauver ?\n\nMoon désigne l’extrémité du ponton.\n\n— Elle n’a pas besoin de nous. Elle a choisi d’elle-même. Elle est très belle. Elle est nécessairement experte en l’art de repousser les avances des types du genre de Skky, sinon elle ne serait pas là.\n\n— Tu vas la mettre en danger.\n\n— Non, elle se contrôle déjà. Simplement, elle n’a pas peur de la mort.\n\n— Comme une toxico.\n\n— Exactement, l’instant du boost surpasse l’éternité. Qui n’a pas connu l’extase n’est qu’à demi-vivant. Cette fille a été initiée il y a longtemps."
}