{
  "id": "2_86",
  "title": "Chapitre 86",
  "lieu": "Discovery Island, Bahamas",
  "heure": "15:45",
  "texte": "Skky ne parcourt la trame qu’avec légèreté, sans la marquer de toute la gravité de sa conscience, juste avec assez de pression pour creuser une pente en direction de son temple. Savannah imagine le gourou comme une fleur carnivore dans laquelle les insectes glissent irrémédiablement. Elle refuse de se faire gober. Elle passe de plus en plus de temps loin des autres analystes.\n\nPerchée sur un rocher, elle contemple la mer baigner les hauts fonds sablonneux. Elle aime la transparence, les jeux de miroir, les variations chromatiques. Elle aime la solitude, cette banale opportunité d’être elle-même, ce qui la renvoie immanquablement à l’enseignement de Skky et à ses trois piliers d’une vie équilibrée.\n\n1/ Se connecter au réseau, donc communier.\n\n2/ Se connecter au corps, donc baiser, faire du sport.\n\n3/ Se connecter à l’indicible, donc méditer.\n\nSavannah s’en veut d’être d’accord avec cette recette simpliste. Elle a sacrifié trop d’années à la trame, reliée à l’humanité avec le seul secours de son cerveau. Un matin, elle n’a plus senti ses jambes et s’est écroulée de faiblesse, pauvre chose que le biologique en elle ne soutenait plus. Elle a rejoint le temple pour se soigner. Pour retrouver la forme physique autant que des moments de méditation. Peu à peu, elle s’est rétablie, avant d’aider ses amis à découvrir la modération salvatrice.\n\nAu final, elle est peut-être plus présente sur la trame qu’avant parce qu’en même temps elle est plus attentive à ses gestes et plus consciente de la totalité des phénomènes. La discipline lui a permis d’avancer plus loin dans la communion, sans pour autant se perdre en chemin.\n\nSavannah ne veut pas imiter les machines zarmiènes. À force de n’être que des êtres réseau, elles sont devenues psychopathes. Elles n’ont que mépris pour la vie, pour l’humanité, pour la beauté. Elles tournent à vide, avec pour désir exclusif de perpétuer leurs réflexes mécaniques. Jamais elles ne se demandent pourquoi. L’existence les pousse à étendre leur sphère d’influence quitte à tout détruire. Elles ressemblent à des virus prêts à sacrifier leur hôte pour démultiplier leur code.\n\nSavannah préfère se tenir à distance de la trame à ce moment décisif de la bataille. Les hypos seront peut-être les seuls à survivre au choc des consciences."
}