{
  "id": "3_92",
  "title": "Chapitre 92",
  "lieu": "Astana, Kazakhstan",
  "heure": "1:45",
  "texte": "— Il se passe quelque chose dans l’espace.\n\nGaliya juge assez fou d’affirmer une chose pareille et de n’oser le dire à personne, et surtout de ne pas le partager dans la trame. Depuis aussi loin qu’elle se souvienne, elle écoute les étoiles. Elle a commencé par tourner l’antenne du poste radio amateur de son père vers le ciel, puis s’est équipée d’une parabole quand elle a rencontré d’autres stardroppers sur le InLine.\n\nGaliya a appris à reconnaître le style propre de centaines d’objets célestes. Les naines jaunes à l’image du soleil ronronnent comme un bateau à moteur poussif. Les géantes rouges sifflent avec la hargne d’un train grande vitesse qui file dans une gare sans ralentir. Les pulsars au bord de la crise cardiaque s’invitent dans des Mix Party. Les modulations dépendent de la taille, de l’âge, de la température. Il s’agit d’une métaphore, de la traduction en sons des ondes électromagnétiques reçues par la parabole. Tout peut-être transposé, recodé, reste une musique qui avec un peu d’entraînement procure autant de plaisir que le bruit du vent dans les arbres ou le bourdonnement des insectes par un chaud après-midi d’été.\n\nGaliya a cessé d’observer des astres en particulier. Plutôt que fixer les ramures d’un saule pleureur, les aigrettes d’un pissenlit, le pont au-dessus de la rivière, elle se tend vers l’ensemble du paysage. Elle tente de le voir tout entier sans s’intéresser à ses détails. Elle suit les chemins, les cours d’eau, les lignes électriques. Son regard vagabonde et jamais ne s’alanguit en un point précis, sinon pour mieux bondir ailleurs. Alors elle communie avec le monde comme avec les étoiles. Quand un avion traverse le ciel, il déchire la toile avec la même violence que des ondes inhabituelles. Impossible de ne pas sursauter et de ne pas ressentir une forme de dégoût.\n\nUn combat se déroule tout là-haut, sur des fréquences artificielles, avec des chaleurs moindres, mais plus concentrées, des jets d’énergie aussi brefs qu’illogiques, sans qu’il soit imaginable de définir les camps en présence. Tout s’arrête, parce que le récepteur a cessé de fonctionner, et qu’autre chose s’est produit, de plus profond, de plus lointain, donc de plus ancien."
}