{
  "id": "4_13",
  "title": "Chapitre 13",
  "lieu": "Anchorage, États-Unis",
  "heure": "11:45",
  "texte": "La matinée s’est évanouie sans que Peter ne réussisse à se mettre au travail, victime de son atavique tendance à la procrastination. Il a toujours de bonnes excuses comme affirmer que telle vidéo trouvée sur InLine est extraordinaire. Il vient de découvrir une conférence InLine Global par Devora Newton. Une trentenaire filiforme, en combinaison de mousseline jaune, les bras nus et chargés de bracelets clinquants, qui coiffe ses cheveux en chignon. Elle commence par raconter comment elle s’est fait virer du MIT après avoir accusé d’attouchements son directeur de thèse.\n\n— J’acceptais ça ou je n’avais aucune chance de poursuivre mes recherches extravagantes.\n\nGros plan sur le public qui se marre. Peter ne tombe pas dans le panneau. Il sent que Devora a envie de régler ses comptes avec un professeur qui n’est pas là pour se défendre. Dans ces histoires, c’est parole contre parole. Cette Devora mérite d’ailleurs d’être tripotée, et pas juste à la surface, d’autant que, côté scientifique, elle plane.\n\nLes machines auraient une conscience esthétique. Elles seraient capables d’apprécier les œuvres d’art. Devora ne sort pas ce résultat de son chapeau, mais presque. Elle remarque que les IA spécialisées dans l’analyse visuelle consacrent plus de temps de calcul aux tableaux de maîtres qu’à ceux d’artistes moins célèbres. Elles s’arrêteraient moins longtemps encore sur les créations des autres machines, comme si elles reconnaissaient un manque de génie.\n\nPas étonnant que le prof ait tenté la dernière chose possible avec cette Devora. Depuis la révolution des foulards en Iran, la résurgence du féminisme exaspère Peter. Elles ont qu’à descendre dans les mines plutôt que balancer des théories insoutenables. Peter a un contre-argument à la thèse farfelue de Devora : les IA s’attardent sur les grandes œuvres parce qu’elles sont plus complexes. Non, répond Devora. Les IA aiment les monochromes de Klein ou de Soulage autant que les compositions polyphoniques du Carpaccio. Ce n’est pas une question de complexité, mais de charge émotionnelle. Peter éclate de rire. Devora a besoin de davantage d’émotions. D’ailleurs cette machine mal baisée plante, tout au moins la vidéo où elle apparaît."
}