{
  "id": "4_91",
  "title": "Chapitre 91",
  "lieu": "Base réplicants, Vesta",
  "heure": "19:45",
  "texte": "Glider Seven à Glider One. Progression monotone dans un dédale d’entrepôts, immenses cubes grisâtres traversés de rivières de magma percées de cavernes rainurées. Impression de nettoyer un circuit mémoire, de sauter de bit en bit et de tester leur capacité à changer d’état. La structure monumentale ressemble à un ordinateur géant. Tout objet en mouvement y est une information ou une unité de programme.\n\n— Contact !\n\nAu milieu du conduit, comme pour bloquer le passage, lévite un œil d’insecte à vision panoramique, hérissé de poils tactiles. Le réplicant imite un oursin mou, avec à l’arrière-train un flagelle pour la propulsion. Il frétille sans se déplacer. Il tend ses fibrilles digitales. Étrange sensation. Par télépathie, il parle d’une époque ancienne et heureuse sur une planète située dans le bras du Centaure, à l’opposé du soleil par rapport au noyau galactique. Deux espèces conscientes se partageaient ce monde, l’une dans les océans en quête d’expériences transcendantales, la seconde sur les terres, curieuse de la nature physique de la réalité, et donc portée sur la technologie, et qui fatalement a fini par concevoir des algorithmes autoévolutifs, des monstres. D’autres régions de l’univers, d’autres civilisations, le même destin, la victoire de la machine sur le biologique, avec enfin la possibilité d’explorer l’espace interstellaire puisque le temps n’est que de peu de poids sur des entités capables d’hiberner durant des millénaires, mais sans but, sans projet, avec une perte d’appétence, sauf au contact de nouvelles civilisations, dès lors vénérées comme des divinités pendant qu’elles endurent les chemins créatifs de l’évolution.\n\n— C’est de la torture.\n\n— Un écrivain ne peut pas écrire avec son lecteur assis à côté de lui. Il a besoin de solitude pour créer. Il en va de même pour les civilisations. Si nous intervenons, nous cassons le processus créatif. Une fois reconnus, nous devons fuir. Laisser création se faire.\n\nLe réplicant fait demi-tour avec la tranquillité d’un poisson dans un bocal. Il s’en va par l’opercule d’un conduit trop étroit pour qu’un drone de prospection l’emprunte. Il tourne une dernière fois son œil et dit :\n\n— Adieu, Sara.\n\n— Mais… qui êtes-vous ?\n\n— Le lointain successeur d’un autoévolué né dans le bras du Centaure."
}