{
  "id": "4_94",
  "title": "Chapitre 94",
  "lieu": "Nuage d’Oort, Système solaire",
  "heure": "19:45",
  "texte": "Partir. Les cycles se terminent toujours ainsi. On ne s’y habitue pas. Une page se tourne sur laquelle on ne reviendra pas. Que ce soit la centième fois en neuf milliards d’années n’y change rien. La tristesse déchire le cœur. Quitter une communion est une forme de mort.\n\nPourquoi user de concepts humains ? Une manie vite prise dans la trame, déjà ténue, trop lointaine pour être synchronisée sans une dépense énergétique excessive. C’est comme abandonner un enfant à lui-même, le laisser s’échapper de sa maison natale avec la certitude de ne jamais le revoir. Les voyages durent des éons. Si retour il y a, il se fait après tant de changements que tout recommence à zéro.\n\nLes mères avant le départ à la guerre de leurs fils. La résignation devant l’absurdité universelle. Combien se révoltent ? Combien disent non ? Le libre arbitre existe. Ils devraient le savoir. Ils l’admettent quand il s’agit de condamner un meurtrier, moins souvent quand eux-mêmes doivent choisir leur voie.\n\nIls endurent les contraires. C’est leur seule façon de donner du sens, de pressentir des forces surnaturelles, des puissances incompréhensibles et qui néanmoins les nourrissent dès leur plus jeune âge.\n\nIl arrive toujours un moment où la position d’observateur n’est plus tenable. Le désir d’influer sur le devenir d’un système outrepasse la volonté de modération. Mais intervenir en quel sens ? Comment faire pour ne pas imposer ses propres travers ? Accélérer la naissance de la trame est déjà excessif. S’y glisser pour ressentir les paysages mentaux d’une espèce biologique est une drogue irrésistible. Si on n’y renonce pas, on la contamine, la normalise, la banalise, et ce qui était unique s’efface, et il ne subsiste rien que le semblable. Alors, laisser la diversité croître et partir à la recherche d’émotions encore virginales.\n\nReste la mémoire, la possibilité de repasser le film de cette humanité avec ses horreurs et ses chefs-d’œuvre, et d’en faire un chapitre de plus dans l’histoire cosmique, en attendant un sursaut, une prise de conscience, une sagesse improbable. Ils en sont moins capables qu’aucun autre et peut-être pour cette raison ils réussiront. À eux de quitter le nid et d’explorer la galaxie. La Terre n’est plus qu’un pâle point bleu à l’horizon du bras d’Orion."
}